EasyDB/MongoDB.py
EasyDB/SqliteOperation.py
EasyDB/__init__.py
EasyDB/__version__.py
Easydb_plus-0.0.4.dist-info/LICENSE
Easydb_plus-0.0.4.dist-info/METADATA
Easydb_plus-0.0.4.dist-info/WHEEL
Easydb_plus-0.0.4.dist-info/top_level.txt
Easydb_plus-0.0.4.dist-info/RECORD
